README.rst
setup.cfg
setup.py
changelog/__init__.py
changelog/changelog.py
changelog/timeline.py
changelog/feeds/__init__.py
changelog/feeds/feed.py
changelog/feeds/github.py
changelog/printers/__init__.py
changelog/printers/markdown.py
changelog/printers/printer.py
tiny_changelog.egg-info/PKG-INFO
tiny_changelog.egg-info/SOURCES.txt
tiny_changelog.egg-info/dependency_links.txt
tiny_changelog.egg-info/entry_points.txt
tiny_changelog.egg-info/top_level.txt