Metadata-Version: 1.1
Name: tiny-changelog
Version: 0.9.0
Summary: Tiny Changelog Generator
Home-page: https://github.com/alexanderad/tiny-changelog
Author: Alexander Shchapov
Author-email: alexander.shchapov@gmail.com
License: MIT
Platform: UNKNOWN
Classifier: Development Status :: 4 - Beta
Classifier: Intended Audience :: Developers
Classifier: License :: OSI Approved :: MIT License
Classifier: Programming Language :: Python
Classifier: Programming Language :: Python :: 2.7
